LICENSE
README.md
setup.py
leymosun/__init__.py
leymosun/gaussian.py
leymosun/matrix.py
leymosun/random.py
leymosun/spectral.py
leymosun/stats.py
leymosun/storage.py
leymosun/version.py
leymosun.egg-info/PKG-INFO
leymosun.egg-info/SOURCES.txt
leymosun.egg-info/dependency_links.txt
leymosun.egg-info/not-zip-safe
leymosun.egg-info/requires.txt
leymosun.egg-info/top_level.txt
tests/test_gaussian.py
tests/test_matrix.py
tests/test_random.py
tests/test_spectral.py
tests/test_stats.py