Metadata-Version: 2.1
Name: leymosun
Version: 0.2.51
Summary: High-Entropy Randomness Research Toolkit. High-Entropy Random Number Generator (HE-RNGs).                 Generation of random matrices in canonical ensembles. Generating of mixed matrix ensembles via                 Mixed Matrix Ensemble Sampling (MMES) algorithm.                 Matrix utilities, spectral analysis, spectral unfolding, nearest-neighbor spacing,                 mean adjacent gap ratio, analytic expressions from theory and                 uncertainty quantification tools
Home-page: https://github.com/msuzen/leymosun
Author: M.Suzen
Author-email: suzen@acm.org
License: GPL-3
Provides-Extra: test
License-File: LICENSE
